QuantileRegression/QuantileRegression.py
QuantileRegression/__init__.py
QuantileRegression-0.1.5.dist-info/LICENSE
QuantileRegression-0.1.5.dist-info/METADATA
QuantileRegression-0.1.5.dist-info/WHEEL
QuantileRegression-0.1.5.dist-info/top_level.txt
QuantileRegression-0.1.5.dist-info/RECORD
