Metadata-Version: 2.1
Name: QuantileRegression
Version: 0.1.5
Summary: QuantileRegression package based on SciPy optimization routines.
Home-page: https://github.com/antononcube/Python-packages/tree/main/QuantileRegression
Author: Anton Antonov
Author-email: antononcube@posteo.net
Keywords: quantile regression,quantile,regression,optimization,fit,fitting
Classifier: Intended Audience :: Science/Research
Classifier: Intended Audience :: Developers
Classifier: Programming Language :: Python :: 3
Classifier: License :: OSI Approved :: BSD License
Classifier: Intended Audience :: Science/Research
Classifier: Intended Audience :: Developers
Classifier: Operating System :: OS Independent
Requires-Python: >=3.7
License-File: LICENSE
Requires-Dist: numpy
Requires-Dist: scipy
